luxcorerender-2.0.data/purelib/pyluxcore/__init__.py
luxcorerender-2.0.data/purelib/pyluxcore/libembree.so.2
luxcorerender-2.0.data/purelib/pyluxcore/libtbb.so.2
luxcorerender-2.0.data/purelib/pyluxcore/libtbbmalloc.so.2
luxcorerender-2.0.data/purelib/pyluxcore/pyluxcore.so
luxcorerender-2.0.data/purelib/pyluxcoretools/__init__.py
luxcorerender-2.0.data/purelib/pyluxcoretools/pyluxcoreconsole/__init__.py
luxcorerender-2.0.data/purelib/pyluxcoretools/pyluxcoreconsole/cmd.py
luxcorerender-2.0.data/purelib/pyluxcoretools/pyluxcoremenu/__init__.py
luxcorerender-2.0.data/purelib/pyluxcoretools/pyluxcoremenu/cmd.py
luxcorerender-2.0.data/purelib/pyluxcoretools/pyluxcoremenu/menuwindow.py
luxcorerender-2.0.data/purelib/pyluxcoretools/pyluxcoremerge/__init__.py
luxcorerender-2.0.data/purelib/pyluxcoretools/pyluxcoremerge/cmd.py
luxcorerender-2.0.data/purelib/pyluxcoretools/pyluxcorenetconsole/__init__.py
luxcorerender-2.0.data/purelib/pyluxcoretools/pyluxcorenetconsole/addnodedialog.py
luxcorerender-2.0.data/purelib/pyluxcoretools/pyluxcorenetconsole/cmd.py
luxcorerender-2.0.data/purelib/pyluxcoretools/pyluxcorenetconsole/mainwindow.py
luxcorerender-2.0.data/purelib/pyluxcoretools/pyluxcorenetconsole/ui.py
luxcorerender-2.0.data/purelib/pyluxcoretools/pyluxcorenetnode/__init__.py
luxcorerender-2.0.data/purelib/pyluxcoretools/pyluxcorenetnode/cmd.py
luxcorerender-2.0.data/purelib/pyluxcoretools/pyluxcorenetnode/mainwindow.py
luxcorerender-2.0.data/purelib/pyluxcoretools/pyluxcorenetnode/ui.py
luxcorerender-2.0.data/purelib/pyluxcoretools/renderfarm/__init__.py
luxcorerender-2.0.data/purelib/pyluxcoretools/renderfarm/renderfarm.py
luxcorerender-2.0.data/purelib/pyluxcoretools/renderfarm/renderfarmfilmmerger.py
luxcorerender-2.0.data/purelib/pyluxcoretools/renderfarm/renderfarmjobsingleimage.py
luxcorerender-2.0.data/purelib/pyluxcoretools/renderfarm/renderfarmnode.py
luxcorerender-2.0.data/purelib/pyluxcoretools/utils/__init__.py
luxcorerender-2.0.dist-info/DESCRIPTION.rst
luxcorerender-2.0.dist-info/METADATA
luxcorerender-2.0.dist-info/RECORD
luxcorerender-2.0.dist-info/WHEEL
luxcorerender-2.0.dist-info/metadata.json
luxcorerender-2.0.dist-info/top_level.txt
