Metadata-Version: 2.0
Name: luxcorerender
Version: 2.0
Summary: LuxCore API
Home-page: https://www.luxcorerender.org
Author: LuxCoreRender Project
Author-email: admin@luxcorerender.org
License: UNKNOWN
Keywords: raytracing rendering
Platform: UNKNOWN
Classifier: Development Status :: 3 - Alpha
Classifier: Intended Audience :: Developers
Classifier: Topic :: Multimedia :: Graphics :: 3D Rendering
Classifier: License :: OSI Approved :: Apache Software License
Classifier: Programming Language :: Python :: 3.4
